hsp/__init__.py
hsp/exception.py
hsp/hsp.py
hsp/stream.py
hsp-0.1.0.dist-info/METADATA
hsp-0.1.0.dist-info/WHEEL
hsp-0.1.0.dist-info/top_level.txt
hsp-0.1.0.dist-info/zip-safe
hsp-0.1.0.dist-info/RECORD
