Metadata-Version: 2.1
Name: hsp
Version: 0.1.0
Summary: python+trio implementation of HSP
Home-page: UNKNOWN
Author: Jörn Heissler
License: MIT
Keywords: hsp,trio
Platform: UNKNOWN
Classifier: Development Status :: 4 - Beta
Classifier: License :: OSI Approved :: MIT License
Classifier: Intended Audience :: Developers
Classifier: Programming Language :: Python :: 3.5
Classifier: Programming Language :: Python :: 3.6
Classifier: Programming Language :: Python :: 3.7
Requires-Python: >= 3.5.3
Requires-Dist: attrs
Requires-Dist: trio
